{
    "DATA_CENTRE": "CCHDO",
    "N_PROF": 30,
    "POSITIONING_SYSTEM": "GPS",
    "_id": "18HU19940524_NPROF_30",
    "btm_depth": null,
    "cast": 2,
    "cruise_url": "https://cchdo.ucsd.edu/cruise/18HU19940524",
    "data_filename": "18HU19940524_hy1.csv.nc",
    "date": "1994-06-03T16:00:00",
    "date_formatted": "1994-06-03",
    "expocode": "18HU19940524",
    "geoLocation": {
        "coordinates": [
            -53.6037,
            55.6095
        ],
        "type": "Point"
    },
    "id": "18HU19940524_NPROF_30",
    "lat": 55.6095,
    "lon": -53.6037,
    "measurements": [
        {
            "DOXY": 288.0,
            "DOXY_qc": 2.0,
            "PRES": 6.2,
            "PSAL": 33.787498474121094,
            "PSAL_qc": 2.0,
            "TEMP": 1.4364999532699585,
            "bottle_number": "23",
            "bottle_number_qc": 3.0,
            "bottle_salinity": 33.81039810180664,
            "bottle_salinity_qc": 4.0,
            "carbon_tetrachloride": 12.871999740600586,
            "carbon_tetrachloride_qc": 3.0,
            "cfc_11": 5.790999889373779,
            "cfc_113": 0.7689999938011169,
            "cfc_113_qc": 2.0,
            "cfc_11_qc": 2.0,
            "cfc_12": 2.9179999828338623,
            "cfc_12_qc": 2.0,
            "methyl_chloroform": 21.222999572753906,
            "methyl_chloroform_qc": 2.0,
            "nitrate": 7.440000057220459,
            "nitrate_qc": 4.0,
            "oxygen": 378.6000061035156,
            "oxygen_qc": 2.0,
            "phosphate": 0.699999988079071,
            "phosphate_qc": 4.0,
            "potential_temperature_c": 1.4362000226974487,
            "sample": "140623",
            "silicate": 6.050000190734863,
            "silicate_qc": 4.0,
            "total_carbon": 2054.199951171875,
            "total_carbon_qc": 2.0
        },
        {
            "DOXY": 251.8000030517578,
            "DOXY_qc": 2.0,
            "PRES": 51.7,
            "PSAL": 34.50149917602539,
            "PSAL_qc": 2.0,
            "TEMP": 1.7872999906539917,
            "bottle_number": "22",
            "bottle_number_qc": 3.0,
            "bottle_salinity": 34.88019943237305,
            "bottle_salinity_qc": 3.0,
            "carbon_tetrachloride": 9.569999694824219,
            "carbon_tetrachloride_qc": 6.0,
            "cfc_11": 4.790999889373779,
            "cfc_113": 0.5730000138282776,
            "cfc_113_qc": 6.0,
            "cfc_11_qc": 6.0,
            "cfc_12": 2.36299991607666,
            "cfc_12_qc": 6.0,
            "methyl_chloroform": 13.876999855041504,
            "methyl_chloroform_qc": 6.0,
            "nitrate": 12.970000267028809,
            "nitrate_qc": 4.0,
            "oxygen": 324.20001220703125,
            "oxygen_qc": 2.0,
            "phosphate": 1.0800000429153442,
            "phosphate_qc": 4.0,
            "potential_temperature_c": 1.7847000360488892,
            "sample": "140622",
            "silicate": 7.539999961853027,
            "silicate_qc": 4.0,
            "total_carbon": 2110.0,
            "total_carbon_qc": 2.0
        },
        {
            "DOXY": 232.3000030517578,
            "DOXY_qc": 2.0,
            "PRES": 94.3,
            "PSAL": 34.80839920043945,
            "PSAL_qc": 2.0,
            "TEMP": 3.635499954223633,
            "bottle_number": "21",
            "bottle_number_qc": 2.0,
            "bottle_salinity": 34.80699920654297,
            "bottle_salinity_qc": 2.0,
            "carbon_tetrachloride": 7.875,
            "carbon_tetrachloride_qc": 2.0,
            "cfc_11": 3.9839999675750732,
            "cfc_113": 0.4519999921321869,
            "cfc_113_qc": 2.0,
            "cfc_11_qc": 2.0,
            "cfc_12": 2.1419999599456787,
            "cfc_12_qc": 2.0,
            "methyl_chloroform": 15.258999824523926,
            "methyl_chloroform_qc": 2.0,
            "nitrate": 14.75,
            "nitrate_qc": 6.0,
            "oxygen": 297.20001220703125,
            "oxygen_qc": 2.0,
            "phosphate": 1.1799999475479126,
            "phosphate_qc": 6.0,
            "potential_temperature_c": 3.629199981689453,
            "sample": "140621",
            "silicate": 8.8100004196167,
            "silicate_qc": 6.0,
            "total_carbon": 2128.199951171875,
            "total_carbon_qc": 2.0
        },
        {
            "DOXY": 232.89999389648438,
            "DOXY_qc": 2.0,
            "PRES": 186.2,
            "PSAL": 34.84830093383789,
            "PSAL_qc": 2.0,
            "TEMP": 3.7279000282287598,
            "bottle_number": "20",
            "bottle_number_qc": 2.0,
            "bottle_salinity": 34.848899841308594,
            "bottle_salinity_qc": 2.0,
            "carbon_tetrachloride": 7.676000118255615,
            "carbon_tetrachloride_qc": 2.0,
            "cfc_11": 3.8540000915527344,
            "cfc_113": 0.4259999990463257,
            "cfc_113_qc": 2.0,
            "cfc_11_qc": 2.0,
            "cfc_12": 2.052000045776367,
            "cfc_12_qc": 2.0,
            "methyl_chloroform": 15.470999717712402,
            "methyl_chloroform_qc": 2.0,
            "nitrate": 15.130000114440918,
            "nitrate_qc": 6.0,
            "oxygen": 295.1000061035156,
            "oxygen_qc": 2.0,
            "phosphate": 1.2000000476837158,
            "phosphate_qc": 6.0,
            "potential_temperature_c": 3.7153000831604004,
            "sample": "140620",
            "silicate": 9.600000381469727,
            "silicate_qc": 6.0,
            "total_carbon": 2164.699951171875,
            "total_carbon_qc": 2.0
        },
        {
            "DOXY": 235.60000610351562,
            "DOXY_qc": 2.0,
            "PRES": 330.0,
            "PSAL": 34.876800537109375,
            "PSAL_qc": 2.0,
            "TEMP": 3.6891000270843506,
            "bottle_number": "19",
            "bottle_number_qc": 2.0,
            "bottle_salinity": 34.87820053100586,
            "bottle_salinity_qc": 2.0,
            "carbon_tetrachloride": 7.380000114440918,
            "carbon_tetrachloride_qc": 2.0,
            "cfc_11": 3.677999973297119,
            "cfc_113": 0.39500001072883606,
            "cfc_113_qc": 2.0,
            "cfc_11_qc": 2.0,
            "cfc_12": 2.0239999294281006,
            "cfc_12_qc": 2.0,
            "methyl_chloroform": 14.03499984741211,
            "methyl_chloroform_qc": 2.0,
            "nitrate": 15.630000114440918,
            "nitrate_qc": 6.0,
            "oxygen": 296.0,
            "oxygen_qc": 2.0,
            "phosphate": 1.2100000381469727,
            "phosphate_qc": 6.0,
            "potential_temperature_c": 3.6663999557495117,
            "sample": "140619",
            "silicate": 9.319999694824219,
            "silicate_qc": 6.0,
            "total_carbon": 1390.4000244140625,
            "total_carbon_qc": 4.0
        },
        {
            "DOXY": 237.10000610351562,
            "DOXY_qc": 2.0,
            "PRES": 530.1,
            "PSAL": 34.876800537109375,
            "PSAL_qc": 2.0,
            "TEMP": 3.482300043106079,
            "bottle_number": "18",
            "bottle_number_qc": 2.0,
            "bottle_salinity": 34.875999450683594,
            "bottle_salinity_qc": 2.0,
            "carbon_tetrachloride": 7.2210001945495605,
            "carbon_tetrachloride_qc": 2.0,
            "cfc_11": 3.5510001182556152,
            "cfc_113": 0.49900001287460327,
            "cfc_113_qc": 3.0,
            "cfc_11_qc": 2.0,
            "cfc_12": 1.9249999523162842,
            "cfc_12_qc": 2.0,
            "methyl_chloroform": 13.812000274658203,
            "methyl_chloroform_qc": 2.0,
            "nitrate": 15.8100004196167,
            "nitrate_qc": 6.0,
            "oxygen": 296.3999938964844,
            "oxygen_qc": 2.0,
            "phosphate": 1.2200000286102295,
            "phosphate_qc": 6.0,
            "potential_temperature_c": 3.4458999633789062,
            "sample": "140618",
            "silicate": 9.630000114440918,
            "silicate_qc": 6.0,
            "total_carbon": 1398.300048828125,
            "total_carbon_qc": 4.0
        },
        {
            "DOXY": 240.5,
            "DOXY_qc": 2.0,
            "PRES": 734.0,
            "PSAL": 34.86090087890625,
            "PSAL_qc": 2.0,
            "TEMP": 3.15910005569458,
            "bottle_number": "17",
            "bottle_number_qc": 2.0,
            "bottle_salinity": 34.862998962402344,
            "bottle_salinity_qc": 2.0,
            "carbon_tetrachloride": 7.394999980926514,
            "carbon_tetrachloride_qc": 2.0,
            "cfc_11": 3.434000015258789,
            "cfc_113": 0.31299999356269836,
            "cfc_113_qc": 2.0,
            "cfc_11_qc": 2.0,
            "cfc_12": 1.9359999895095825,
            "cfc_12_qc": 2.0,
            "methyl_chloroform": 13.35200023651123,
            "methyl_chloroform_qc": 2.0,
            "nitrate": 15.989999771118164,
            "nitrate_qc": 6.0,
            "oxygen": 297.8999938964844,
            "oxygen_qc": 2.0,
            "phosphate": 1.2200000286102295,
            "phosphate_qc": 6.0,
            "potential_temperature_c": 3.1094000339508057,
            "sample": "140617",
            "silicate": 9.710000038146973,
            "silicate_qc": 6.0,
            "total_carbon": NaN,
            "total_carbon_qc": 5.0
        },
        {
            "DOXY": 239.0,
            "DOXY_qc": 2.0,
            "PRES": 928.9,
            "PSAL": 34.85350036621094,
            "PSAL_qc": 2.0,
            "TEMP": 3.056299924850464,
            "bottle_number": "16",
            "bottle_number_qc": 2.0,
            "bottle_salinity": 34.85240173339844,
            "bottle_salinity_qc": 2.0,
            "carbon_tetrachloride": 7.269999980926514,
            "carbon_tetrachloride_qc": 2.0,
            "cfc_11": 3.4639999866485596,
            "cfc_113": 0.32600000500679016,
            "cfc_113_qc": 2.0,
            "cfc_11_qc": 2.0,
            "cfc_12": 1.7970000505447388,
            "cfc_12_qc": 2.0,
            "methyl_chloroform": 13.201000213623047,
            "methyl_chloroform_qc": 2.0,
            "nitrate": 16.049999237060547,
            "nitrate_qc": 6.0,
            "oxygen": 300.6000061035156,
            "oxygen_qc": 2.0,
            "phosphate": 1.2000000476837158,
            "phosphate_qc": 6.0,
            "potential_temperature_c": 2.992799997329712,
            "sample": "140616",
            "silicate": 9.710000038146973,
            "silicate_qc": 6.0,
            "total_carbon": NaN,
            "total_carbon_qc": 5.0
        },
        {
            "DOXY": 241.3000030517578,
            "DOXY_qc": 2.0,
            "PRES": 1126.9,
            "PSAL": 34.84149932861328,
            "PSAL_qc": 2.0,
            "TEMP": 2.922499895095825,
            "bottle_number": "15",
            "bottle_number_qc": 2.0,
            "bottle_salinity": 34.84389877319336,
            "bottle_salinity_qc": 2.0,
            "carbon_tetrachloride": 7.4670000076293945,
            "carbon_tetrachloride_qc": 2.0,
            "cfc_11": 3.5239999294281006,
            "cfc_113": 0.3540000021457672,
            "cfc_113_qc": 2.0,
            "cfc_11_qc": 2.0,
            "cfc_12": 1.8450000286102295,
            "cfc_12_qc": 2.0,
            "methyl_chloroform": 13.869999885559082,
            "methyl_chloroform_qc": 2.0,
            "nitrate": 15.850000381469727,
            "nitrate_qc": 6.0,
            "oxygen": 303.79998779296875,
            "oxygen_qc": 2.0,
            "phosphate": 1.2100000381469727,
            "phosphate_qc": 6.0,
            "potential_temperature_c": 2.844899892807007,
            "sample": "140615",
            "silicate": 9.5,
            "silicate_qc": 6.0,
            "total_carbon": 2131.89990234375,
            "total_carbon_qc": 3.0
        },
        {
            "DOXY": 240.8000030517578,
            "DOXY_qc": 2.0,
            "PRES": 1331.3,
            "PSAL": 34.84560012817383,
            "PSAL_qc": 2.0,
            "TEMP": 2.909600019454956,
            "bottle_number": "14",
            "bottle_number_qc": 2.0,
            "bottle_salinity": 34.84510040283203,
            "bottle_salinity_qc": 2.0,
            "carbon_tetrachloride": 7.074999809265137,
            "carbon_tetrachloride_qc": 2.0,
            "cfc_11": 3.3320000171661377,
            "cfc_113": 0.34200000762939453,
            "cfc_113_qc": 2.0,
            "cfc_11_qc": 2.0,
            "cfc_12": 1.753999948501587,
            "cfc_12_qc": 2.0,
            "methyl_chloroform": 13.211000442504883,
            "methyl_chloroform_qc": 2.0,
            "nitrate": 15.899999618530273,
            "nitrate_qc": 6.0,
            "oxygen": 302.3999938964844,
            "oxygen_qc": 2.0,
            "phosphate": 1.2100000381469727,
            "phosphate_qc": 6.0,
            "potential_temperature_c": 2.8159000873565674,
            "sample": "140614",
            "silicate": 9.670000076293945,
            "silicate_qc": 6.0,
            "total_carbon": 2131.5,
            "total_carbon_qc": 3.0
        },
        {
            "DOXY": 238.1999969482422,
            "DOXY_qc": 2.0,
            "PRES": 1531.0,
            "PSAL": 34.84830093383789,
            "PSAL_qc": 2.0,
            "TEMP": 2.91129994392395,
            "bottle_number": "13",
            "bottle_number_qc": 2.0,
            "bottle_salinity": 34.84859848022461,
            "bottle_salinity_qc": 2.0,
            "carbon_tetrachloride": 6.96999979019165,
            "carbon_tetrachloride_qc": 2.0,
            "cfc_11": 3.2990000247955322,
            "cfc_113": 0.3490000069141388,
            "cfc_113_qc": 2.0,
            "cfc_11_qc": 2.0,
            "cfc_12": 1.7400000095367432,
            "cfc_12_qc": 2.0,
            "methyl_chloroform": 12.482000350952148,
            "methyl_chloroform_qc": 2.0,
            "nitrate": 15.850000381469727,
            "nitrate_qc": 6.0,
            "oxygen": 302.6000061035156,
            "oxygen_qc": 2.0,
            "phosphate": 1.2000000476837158,
            "phosphate_qc": 6.0,
            "potential_temperature_c": 2.8011999130249023,
            "sample": "140613",
            "silicate": 9.739999771118164,
            "silicate_qc": 6.0,
            "total_carbon": 2132.10009765625,
            "total_carbon_qc": 3.0
        },
        {
            "DOXY": 235.5,
            "DOXY_qc": 2.0,
            "PRES": 1728.5,
            "PSAL": 34.860801696777344,
            "PSAL_qc": 2.0,
            "TEMP": 2.9416000843048096,
            "bottle_number": "12",
            "bottle_number_qc": 3.0,
            "bottle_salinity": 34.88740158081055,
            "bottle_salinity_qc": 4.0,
            "carbon_tetrachloride": 6.519999980926514,
            "carbon_tetrachloride_qc": 6.0,
            "cfc_11": 2.9619998931884766,
            "cfc_113": 0.5210000276565552,
            "cfc_113_qc": 3.0,
            "cfc_11_qc": 6.0,
            "cfc_12": 1.5379999876022339,
            "cfc_12_qc": 6.0,
            "methyl_chloroform": 12.550999641418457,
            "methyl_chloroform_qc": 6.0,
            "nitrate": 15.680000305175781,
            "nitrate_qc": 4.0,
            "oxygen": 297.3999938964844,
            "oxygen_qc": 2.0,
            "phosphate": 1.2200000286102295,
            "phosphate_qc": 4.0,
            "potential_temperature_c": 2.814300060272217,
            "sample": "140612",
            "silicate": 10.6899995803833,
            "silicate_qc": 4.0,
            "total_carbon": 2133.5,
            "total_carbon_qc": 3.0
        },
        {
            "DOXY": 228.89999389648438,
            "DOXY_qc": 2.0,
            "PRES": 1929.1,
            "PSAL": 34.890098571777344,
            "PSAL_qc": 2.0,
            "TEMP": 3.0292999744415283,
            "bottle_number": "11",
            "bottle_number_qc": 2.0,
            "bottle_salinity": 34.88800048828125,
            "bottle_salinity_qc": 2.0,
            "carbon_tetrachloride": 5.341000080108643,
            "carbon_tetrachloride_qc": 2.0,
            "cfc_11": 2.3299999237060547,
            "cfc_113": 0.1550000011920929,
            "cfc_113_qc": 2.0,
            "cfc_11_qc": 2.0,
            "cfc_12": 1.2380000352859497,
            "cfc_12_qc": 2.0,
            "methyl_chloroform": 8.946999549865723,
            "methyl_chloroform_qc": 2.0,
            "nitrate": 15.640000343322754,
            "nitrate_qc": 6.0,
            "oxygen": 291.0,
            "oxygen_qc": 2.0,
            "phosphate": 1.2200000286102295,
            "phosphate_qc": 6.0,
            "potential_temperature_c": 2.8828999996185303,
            "sample": "140611",
            "silicate": 10.739999771118164,
            "silicate_qc": 6.0,
            "total_carbon": 2133.699951171875,
            "total_carbon_qc": 3.0
        },
        {
            "DOXY": 227.1999969482422,
            "DOXY_qc": 2.0,
            "PRES": 2132.5,
            "PSAL": 34.901798248291016,
            "PSAL_qc": 2.0,
            "TEMP": 2.915299892425537,
            "bottle_number": "10",
            "bottle_number_qc": 2.0,
            "bottle_salinity": 34.901100158691406,
            "bottle_salinity_qc": 2.0,
            "carbon_tetrachloride": 5.297999858856201,
            "carbon_tetrachloride_qc": 2.0,
            "cfc_11": 1.9910000562667847,
            "cfc_113": 0.10999999940395355,
            "cfc_113_qc": 2.0,
            "cfc_11_qc": 2.0,
            "cfc_12": 1.0490000247955322,
            "cfc_12_qc": 2.0,
            "methyl_chloroform": 7.543000221252441,
            "methyl_chloroform_qc": 2.0,
            "nitrate": 15.279999732971191,
            "nitrate_qc": 6.0,
            "oxygen": 287.8999938964844,
            "oxygen_qc": 2.0,
            "phosphate": 1.2200000286102295,
            "phosphate_qc": 6.0,
            "potential_temperature_c": 2.752000093460083,
            "sample": "140610",
            "silicate": 11.210000038146973,
            "silicate_qc": 6.0,
            "total_carbon": 2134.699951171875,
            "total_carbon_qc": 3.0
        },
        {
            "DOXY": 226.8000030517578,
            "DOXY_qc": 2.0,
            "PRES": 2335.4,
            "PSAL": 34.906898498535156,
            "PSAL_qc": 2.0,
            "TEMP": 2.731100082397461,
            "bottle_number": "9",
            "bottle_number_qc": 2.0,
            "bottle_salinity": 34.90620040893555,
            "bottle_salinity_qc": 2.0,
            "carbon_tetrachloride": 4.431000232696533,
            "carbon_tetrachloride_qc": 2.0,
            "cfc_11": 1.9110000133514404,
            "cfc_113": 0.11999999731779099,
            "cfc_113_qc": 2.0,
            "cfc_11_qc": 2.0,
            "cfc_12": 1.0010000467300415,
            "cfc_12_qc": 2.0,
            "methyl_chloroform": 7.355000019073486,
            "methyl_chloroform_qc": 2.0,
            "nitrate": 14.989999771118164,
            "nitrate_qc": 6.0,
            "oxygen": 288.0,
            "oxygen_qc": 2.0,
            "phosphate": 1.2000000476837158,
            "phosphate_qc": 6.0,
            "potential_temperature_c": 2.5518999099731445,
            "sample": "140609",
            "silicate": 11.710000038146973,
            "silicate_qc": 6.0,
            "total_carbon": 2135.199951171875,
            "total_carbon_qc": 3.0
        },
        {
            "DOXY": 229.1999969482422,
            "DOXY_qc": 2.0,
            "PRES": 2535.1,
            "PSAL": 34.902099609375,
            "PSAL_qc": 2.0,
            "TEMP": 2.464099884033203,
            "bottle_number": "8",
            "bottle_number_qc": 2.0,
            "bottle_salinity": 34.900901794433594,
            "bottle_salinity_qc": 2.0,
            "carbon_tetrachloride": 4.945000171661377,
            "carbon_tetrachloride_qc": 2.0,
            "cfc_11": 1.9079999923706055,
            "cfc_113": 0.10700000077486038,
            "cfc_113_qc": 2.0,
            "cfc_11_qc": 2.0,
            "cfc_12": 1.0920000076293945,
            "cfc_12_qc": 2.0,
            "methyl_chloroform": 7.322000026702881,
            "methyl_chloroform_qc": 2.0,
            "nitrate": 14.850000381469727,
            "nitrate_qc": 6.0,
            "oxygen": 288.20001220703125,
            "oxygen_qc": 2.0,
            "phosphate": 1.2300000190734863,
            "phosphate_qc": 6.0,
            "potential_temperature_c": 2.2708001136779785,
            "sample": "140608",
            "silicate": 12.09000015258789,
            "silicate_qc": 6.0,
            "total_carbon": 2136.199951171875,
            "total_carbon_qc": 3.0
        },
        {
            "DOXY": 235.8000030517578,
            "DOXY_qc": 2.0,
            "PRES": 2738.1,
            "PSAL": 34.88850021362305,
            "PSAL_qc": 2.0,
            "TEMP": 2.063199996948242,
            "bottle_number": "7",
            "bottle_number_qc": 2.0,
            "bottle_salinity": 34.887901306152344,
            "bottle_salinity_qc": 2.0,
            "carbon_tetrachloride": 5.119999885559082,
            "carbon_tetrachloride_qc": 2.0,
            "cfc_11": 2.255000114440918,
            "cfc_113": 0.15800000727176666,
            "cfc_113_qc": 2.0,
            "cfc_11_qc": 2.0,
            "cfc_12": 1.1950000524520874,
            "cfc_12_qc": 2.0,
            "methyl_chloroform": 8.97599983215332,
            "methyl_chloroform_qc": 2.0,
            "nitrate": 14.640000343322754,
            "nitrate_qc": 6.0,
            "oxygen": 294.29998779296875,
            "oxygen_qc": 2.0,
            "phosphate": 1.159999966621399,
            "phosphate_qc": 6.0,
            "potential_temperature_c": 1.8583999872207642,
            "sample": "140607",
            "silicate": 11.770000457763672,
            "silicate_qc": 6.0,
            "total_carbon": 2134.89990234375,
            "total_carbon_qc": 3.0
        },
        {
            "DOXY": 241.5,
            "DOXY_qc": 2.0,
            "PRES": 2840.3,
            "PSAL": 34.87620162963867,
            "PSAL_qc": 2.0,
            "TEMP": 1.704699993133545,
            "bottle_number": "6",
            "bottle_number_qc": 2.0,
            "bottle_salinity": 34.87630081176758,
            "bottle_salinity_qc": 2.0,
            "carbon_tetrachloride": 5.671000003814697,
            "carbon_tetrachloride_qc": 2.0,
            "cfc_11": 2.6649999618530273,
            "cfc_113": 0.20000000298023224,
            "cfc_113_qc": 2.0,
            "cfc_11_qc": 2.0,
            "cfc_12": 1.3930000066757202,
            "cfc_12_qc": 2.0,
            "methyl_chloroform": 10.13700008392334,
            "methyl_chloroform_qc": 2.0,
            "nitrate": 14.119999885559082,
            "nitrate_qc": 6.0,
            "oxygen": 298.29998779296875,
            "oxygen_qc": 2.0,
            "phosphate": 1.149999976158142,
            "phosphate_qc": 6.0,
            "potential_temperature_c": 1.4975999593734741,
            "sample": "140606",
            "silicate": 11.180000305175781,
            "silicate_qc": 6.0,
            "total_carbon": 2135.199951171875,
            "total_carbon_qc": 3.0
        },
        {
            "DOXY": 245.1999969482422,
            "DOXY_qc": 2.0,
            "PRES": 2929.3,
            "PSAL": 34.8734016418457,
            "PSAL_qc": 2.0,
            "TEMP": 1.6384999752044678,
            "bottle_number": "5",
            "bottle_number_qc": 2.0,
            "bottle_salinity": 34.872398376464844,
            "bottle_salinity_qc": 2.0,
            "carbon_tetrachloride": 5.888000011444092,
            "carbon_tetrachloride_qc": 2.0,
            "cfc_11": 2.6579999923706055,
            "cfc_113": 0.21400000154972076,
            "cfc_113_qc": 2.0,
            "cfc_11_qc": 2.0,
            "cfc_12": 1.3140000104904175,
            "cfc_12_qc": 2.0,
            "methyl_chloroform": 10.397000312805176,
            "methyl_chloroform_qc": 2.0,
            "nitrate": 14.079999923706055,
            "nitrate_qc": 6.0,
            "oxygen": 299.79998779296875,
            "oxygen_qc": 2.0,
            "phosphate": 1.1399999856948853,
            "phosphate_qc": 6.0,
            "potential_temperature_c": 1.424399971961975,
            "sample": "140605",
            "silicate": 11.279999732971191,
            "silicate_qc": 6.0,
            "total_carbon": 2134.0,
            "total_carbon_qc": 3.0
        },
        {
            "DOXY": NaN,
            "DOXY_qc": NaN,
            "PRES": NaN,
            "PSAL": NaN,
            "PSAL_qc": NaN,
            "TEMP": NaN,
            "bottle_number": "",
            "bottle_number_qc": NaN,
            "bottle_salinity": NaN,
            "bottle_salinity_qc": NaN,
            "carbon_tetrachloride": NaN,
            "carbon_tetrachloride_qc": NaN,
            "cfc_11": NaN,
            "cfc_113": NaN,
            "cfc_113_qc": NaN,
            "cfc_11_qc": NaN,
            "cfc_12": NaN,
            "cfc_12_qc": NaN,
            "methyl_chloroform": NaN,
            "methyl_chloroform_qc": NaN,
            "nitrate": NaN,
            "nitrate_qc": NaN,
            "oxygen": NaN,
            "oxygen_qc": NaN,
            "phosphate": NaN,
            "phosphate_qc": NaN,
            "potential_temperature_c": NaN,
            "sample": "",
            "silicate": NaN,
            "silicate_qc": NaN,
            "total_carbon": NaN,
            "total_carbon_qc": NaN
        }
    ],
    "netcdf_url": "",
    "parameters_in_nc_mapping_to_argovis": {
        "bottle_number": "bottle_number",
        "bottle_number_qc": "bottle_number_qc",
        "bottle_salinity": "bottle_salinity",
        "bottle_salinity_qc": "bottle_salinity_qc",
        "carbon_tetrachloride": "carbon_tetrachloride",
        "carbon_tetrachloride_qc": "carbon_tetrachloride_qc",
        "cfc_11": "cfc_11",
        "cfc_113": "cfc_113",
        "cfc_113_qc": "cfc_113_qc",
        "cfc_11_qc": "cfc_11_qc",
        "cfc_12": "cfc_12",
        "cfc_12_qc": "cfc_12_qc",
        "ctd_oxygen": "DOXY",
        "ctd_oxygen_qc": "DOXY_qc",
        "ctd_salinity": "PSAL",
        "ctd_salinity_qc": "PSAL_qc",
        "ctd_temperature": "TEMP",
        "methyl_chloroform": "methyl_chloroform",
        "methyl_chloroform_qc": "methyl_chloroform_qc",
        "nitrate": "nitrate",
        "nitrate_qc": "nitrate_qc",
        "oxygen": "oxygen",
        "oxygen_qc": "oxygen_qc",
        "phosphate": "phosphate",
        "phosphate_qc": "phosphate_qc",
        "potential_temperature_c": "potential_temperature_c",
        "pressure": "PRES",
        "sample": "sample",
        "silicate": "silicate",
        "silicate_qc": "silicate_qc",
        "total_carbon": "total_carbon",
        "total_carbon_qc": "total_carbon_qc"
    },
    "profile_type": "B",
    "roundLat": 55.61,
    "roundLon": -53.604,
    "section_id": "AR07W",
    "station": "46",
    "station_parameters_in_nc": [
        "pressure",
        "latitude",
        "longitude",
        "time",
        "expocode",
        "station",
        "cast",
        "sample",
        "section_id",
        "bottle_number",
        "bottle_number_qc",
        "btm_depth",
        "ctd_temperature",
        "ctd_salinity",
        "ctd_salinity_qc",
        "bottle_salinity",
        "bottle_salinity_qc",
        "ctd_oxygen",
        "ctd_oxygen_qc",
        "oxygen",
        "oxygen_qc",
        "silicate",
        "silicate_qc",
        "nitrate",
        "nitrate_qc",
        "phosphate",
        "phosphate_qc",
        "cfc_11",
        "cfc_11_qc",
        "cfc_12",
        "cfc_12_qc",
        "cfc_113",
        "cfc_113_qc",
        "carbon_tetrachloride",
        "carbon_tetrachloride_qc",
        "methyl_chloroform",
        "methyl_chloroform_qc",
        "total_carbon",
        "total_carbon_qc",
        "potential_temperature_c",
        "profile_type"
    ],
    "strLat": "55.61 N",
    "strLon": "-53.604 E",
    "units": {
        "DOXY": "micromole/kg",
        "DOXY_qc": "",
        "PRES": "decibar",
        "PSAL": "psu",
        "PSAL_qc": "",
        "TEMP": "Celsius",
        "bottle_number": "",
        "bottle_number_qc": "",
        "bottle_salinity": "psu",
        "bottle_salinity_qc": "",
        "carbon_tetrachloride": "pmol/kg",
        "carbon_tetrachloride_qc": "",
        "cfc_11": "pmol/kg",
        "cfc_113": "pmol/kg",
        "cfc_113_qc": "",
        "cfc_11_qc": "",
        "cfc_12": "pmol/kg",
        "cfc_12_qc": "",
        "lat": "degree_north",
        "lon": "degree_east",
        "methyl_chloroform": "pmol/kg",
        "methyl_chloroform_qc": "",
        "nitrate": "micromole/kg",
        "nitrate_qc": "",
        "oxygen": "micromole/kg",
        "oxygen_qc": "",
        "phosphate": "micromole/kg",
        "phosphate_qc": "",
        "potential_temperature_c": "Celsius",
        "sample": "",
        "silicate": "micromole/kg",
        "silicate_qc": "",
        "total_carbon": "micromole/kg",
        "total_carbon_qc": ""
    }
}